ipyprogress/__init__.py
ipyprogress-0.1.0.dist-info/METADATA
ipyprogress-0.1.0.dist-info/WHEEL
ipyprogress-0.1.0.dist-info/top_level.txt
ipyprogress-0.1.0.dist-info/RECORD
